{"foods":[[4,35,24,37,8,12,25,38,11,19],[26,6,17,1,33,10,2,7,16,32],[11,22,31,3,34,25,17,23,38,28],[15,21,11,3,13,17,34,6,9,7],[20,40,24,35,28,39,6,32,21,16]],"round":7569,"start":"2020-01-25T23:34:38+00:00","changes":[{"t":"2020-01-26T04:16:04+00:00","new":7,"old":6,"arena":1,"pirate":1},{"t":"2020-01-26T04:16:04+00:00","new":8,"old":7,"arena":1,"pirate":3},{"t":"2020-01-26T07:02:05+00:00","new":5,"old":6,"arena":4,"pirate":3},{"t":"2020-01-26T07:15:05+00:00","new":6,"old":5,"arena":4,"pirate":3},{"t":"2020-01-26T08:05:04+00:00","new":5,"old":6,"arena":4,"pirate":3},{"t":"2020-01-26T08:16:07+00:00","new":6,"old":5,"arena":4,"pirate":3},{"t":"2020-01-26T08:31:05+00:00","new":5,"old":6,"arena":4,"pirate":3},{"t":"2020-01-26T08:33:04+00:00","new":6,"old":5,"arena":4,"pirate":3},{"t":"2020-01-26T08:34:05+00:00","new":5,"old":6,"arena":4,"pirate":3},{"t":"2020-01-26T08:37:05+00:00","new":6,"old":5,"arena":4,"pirate":3},{"t":"2020-01-26T08:39:05+00:00","new":5,"old":6,"arena":4,"pirate":3},{"t":"2020-01-26T09:31:05+00:00","new":6,"old":5,"arena":4,"pirate":3},{"t":"2020-01-26T09:32:05+00:00","new":5,"old":6,"arena":4,"pirate":3},{"t":"2020-01-26T09:35:06+00:00","new":6,"old":5,"arena":4,"pirate":3},{"t":"2020-01-26T09:43:05+00:00","new":3,"old":4,"arena":0,"pirate":4},{"t":"2020-01-26T10:52:05+00:00","new":5,"old":6,"arena":4,"pirate":3},{"t":"2020-01-26T10:53:04+00:00","new":6,"old":5,"arena":4,"pirate":3},{"t":"2020-01-26T10:57:06+00:00","new":5,"old":6,"arena":4,"pirate":3},{"t":"2020-01-26T11:35:05+00:00","new":6,"old":5,"arena":4,"pirate":3},{"t":"2020-01-26T11:52:05+00:00","new":5,"old":6,"arena":4,"pirate":3},{"t":"2020-01-26T11:53:05+00:00","new":6,"old":5,"arena":4,"pirate":3},{"t":"2020-01-26T12:00:04+00:00","new":4,"old":3,"arena":0,"pirate":4},{"t":"2020-01-26T12:01:05+00:00","new":3,"old":4,"arena":0,"pirate":4},{"t":"2020-01-26T12:02:06+00:00","new":4,"old":3,"arena":0,"pirate":4},{"t":"2020-01-26T12:05:05+00:00","new":3,"old":4,"arena":0,"pirate":4},{"t":"2020-01-26T12:06:05+00:00","new":4,"old":3,"arena":0,"pirate":4},{"t":"2020-01-26T12:06:05+00:00","new":5,"old":6,"arena":4,"pirate":3},{"t":"2020-01-26T12:07:08+00:00","new":6,"old":5,"arena":4,"pirate":3},{"t":"2020-01-26T12:11:09+00:00","new":3,"old":4,"arena":0,"pirate":4},{"t":"2020-01-26T12:14:05+00:00","new":4,"old":3,"arena":0,"pirate":4},{"t":"2020-01-26T12:15:05+00:00","new":3,"old":4,"arena":0,"pirate":4},{"t":"2020-01-26T12:16:04+00:00","new":4,"old":3,"arena":0,"pirate":4},{"t":"2020-01-26T12:36:04+00:00","new":3,"old":4,"arena":0,"pirate":4},{"t":"2020-01-26T12:42:05+00:00","new":4,"old":3,"arena":0,"pirate":4},{"t":"2020-01-26T12:49:05+00:00","new":3,"old":4,"arena":0,"pirate":4},{"t":"2020-01-26T12:52:05+00:00","new":4,"old":3,"arena":0,"pirate":4},{"t":"2020-01-26T12:55:04+00:00","new":3,"old":4,"arena":0,"pirate":4},{"t":"2020-01-26T12:58:08+00:00","new":4,"old":3,"arena":0,"pirate":4},{"t":"2020-01-26T13:00:05+00:00","new":3,"old":4,"arena":0,"pirate":4},{"t":"2020-01-26T13:01:06+00:00","new":4,"old":3,"arena":0,"pirate":4},{"t":"2020-01-26T13:19:06+00:00","new":3,"old":4,"arena":0,"pirate":4},{"t":"2020-01-26T13:20:05+00:00","new":4,"old":3,"arena":0,"pirate":4},{"t":"2020-01-26T13:23:05+00:00","new":3,"old":4,"arena":0,"pirate":4},{"t":"2020-01-26T13:24:05+00:00","new":4,"old":3,"arena":0,"pirate":4},{"t":"2020-01-26T13:29:05+00:00","new":3,"old":4,"arena":0,"pirate":4},{"t":"2020-01-26T13:31:05+00:00","new":4,"old":3,"arena":0,"pirate":4},{"t":"2020-01-26T13:54:05+00:00","new":3,"old":4,"arena":0,"pirate":4},{"t":"2020-01-26T13:59:05+00:00","new":4,"old":3,"arena":0,"pirate":4},{"t":"2020-01-26T14:03:06+00:00","new":3,"old":4,"arena":0,"pirate":4},{"t":"2020-01-26T14:05:05+00:00","new":4,"old":3,"arena":0,"pirate":4},{"t":"2020-01-26T14:07:06+00:00","new":5,"old":6,"arena":4,"pirate":3},{"t":"2020-01-26T14:08:08+00:00","new":3,"old":4,"arena":0,"pirate":4},{"t":"2020-01-26T14:08:08+00:00","new":6,"old":5,"arena":4,"pirate":3},{"t":"2020-01-26T14:09:05+00:00","new":4,"old":3,"arena":0,"pirate":4},{"t":"2020-01-26T14:17:05+00:00","new":3,"old":4,"arena":0,"pirate":4},{"t":"2020-01-26T14:18:05+00:00","new":4,"old":3,"arena":0,"pirate":4},{"t":"2020-01-26T14:19:05+00:00","new":5,"old":6,"arena":4,"pirate":3},{"t":"2020-01-26T15:40:05+00:00","new":3,"old":4,"arena":0,"pirate":4},{"t":"2020-01-26T16:54:05+00:00","new":4,"old":3,"arena":0,"pirate":4},{"t":"2020-01-26T16:55:05+00:00","new":3,"old":4,"arena":0,"pirate":4},{"t":"2020-01-26T16:56:06+00:00","new":4,"old":3,"arena":0,"pirate":4},{"t":"2020-01-26T17:01:05+00:00","new":3,"old":4,"arena":0,"pirate":4},{"t":"2020-01-26T17:36:05+00:00","new":4,"old":3,"arena":0,"pirate":4},{"t":"2020-01-26T17:37:05+00:00","new":3,"old":4,"arena":0,"pirate":4},{"t":"2020-01-26T20:46:06+00:00","new":2,"old":3,"arena":2,"pirate":2},{"t":"2020-01-26T21:06:05+00:00","new":4,"old":3,"arena":0,"pirate":4}],"pirates":[[18,16,13,20],[3,9,10,12],[6,5,19,17],[2,7,8,15],[14,4,11,1]],"winners":[2,4,3,4,4],"timestamp":"2020-01-26T23:34:32+00:00","lastChange":"2020-01-26T21:06:05+00:00","lastUpdate":"2020-01-26T23:34:32+00:00","currentOdds":[[1,13,2,3,4],[1,7,13,8,2],[1,13,2,2,2],[1,13,13,13,2],[1,13,2,5,2]],"openingOdds":[[1,13,2,3,4],[1,6,13,7,2],[1,13,3,2,2],[1,13,13,13,2],[1,13,2,6,2]]}