{"foods":[[34,26,14,4,17,21,32,28,31,8],[9,35,33,3,31,27,5,12,17,16],[10,27,24,37,13,40,38,39,7,18],[17,23,8,30,14,26,21,11,25,18],[26,28,30,4,29,17,20,36,22,2]],"round":7597,"start":"2020-02-22T23:36:41+00:00","changes":[{"t":"2020-02-23T04:08:05+00:00","new":10,"old":7,"arena":0,"pirate":2},{"t":"2020-02-23T04:08:05+00:00","new":13,"old":12,"arena":0,"pirate":4},{"t":"2020-02-23T06:42:04+00:00","new":5,"old":4,"arena":3,"pirate":4},{"t":"2020-02-23T07:52:07+00:00","new":6,"old":7,"arena":2,"pirate":3},{"t":"2020-02-23T08:14:06+00:00","new":7,"old":6,"arena":2,"pirate":3},{"t":"2020-02-23T08:19:04+00:00","new":6,"old":7,"arena":2,"pirate":3},{"t":"2020-02-23T09:12:05+00:00","new":7,"old":6,"arena":2,"pirate":3},{"t":"2020-02-23T09:30:05+00:00","new":6,"old":7,"arena":2,"pirate":3},{"t":"2020-02-23T09:35:08+00:00","new":7,"old":6,"arena":2,"pirate":3},{"t":"2020-02-23T09:39:09+00:00","new":6,"old":7,"arena":2,"pirate":3},{"t":"2020-02-23T09:49:08+00:00","new":7,"old":6,"arena":2,"pirate":3},{"t":"2020-02-23T09:51:09+00:00","new":6,"old":7,"arena":2,"pirate":3},{"t":"2020-02-23T09:52:05+00:00","new":7,"old":6,"arena":2,"pirate":3},{"t":"2020-02-23T11:28:08+00:00","new":4,"old":5,"arena":3,"pirate":4},{"t":"2020-02-23T11:32:24+00:00","new":6,"old":7,"arena":2,"pirate":3},{"t":"2020-02-23T11:33:05+00:00","new":7,"old":6,"arena":2,"pirate":3},{"t":"2020-02-23T11:42:07+00:00","new":6,"old":7,"arena":2,"pirate":3},{"t":"2020-02-23T11:55:08+00:00","new":7,"old":6,"arena":2,"pirate":3},{"t":"2020-02-23T11:57:08+00:00","new":6,"old":7,"arena":2,"pirate":3},{"t":"2020-02-23T12:01:05+00:00","new":7,"old":6,"arena":2,"pirate":3},{"t":"2020-02-23T12:31:08+00:00","new":6,"old":7,"arena":2,"pirate":3},{"t":"2020-02-23T15:24:08+00:00","new":5,"old":4,"arena":3,"pirate":4},{"t":"2020-02-23T15:25:05+00:00","new":4,"old":5,"arena":3,"pirate":4},{"t":"2020-02-23T15:26:08+00:00","new":5,"old":4,"arena":3,"pirate":4},{"t":"2020-02-23T15:28:08+00:00","new":4,"old":5,"arena":3,"pirate":4},{"t":"2020-02-23T15:29:06+00:00","new":5,"old":4,"arena":3,"pirate":4},{"t":"2020-02-23T15:31:05+00:00","new":4,"old":5,"arena":3,"pirate":4},{"t":"2020-02-23T15:35:05+00:00","new":5,"old":6,"arena":4,"pirate":3},{"t":"2020-02-23T15:35:05+00:00","new":3,"old":2,"arena":4,"pirate":4},{"t":"2020-02-23T15:53:05+00:00","new":7,"old":6,"arena":2,"pirate":3},{"t":"2020-02-23T16:07:08+00:00","new":2,"old":3,"arena":4,"pirate":4},{"t":"2020-02-23T16:08:09+00:00","new":3,"old":2,"arena":4,"pirate":4},{"t":"2020-02-23T16:18:10+00:00","new":2,"old":3,"arena":4,"pirate":4},{"t":"2020-02-23T16:21:08+00:00","new":6,"old":5,"arena":4,"pirate":3},{"t":"2020-02-23T16:22:07+00:00","new":5,"old":6,"arena":4,"pirate":3},{"t":"2020-02-23T17:01:05+00:00","new":6,"old":5,"arena":4,"pirate":3},{"t":"2020-02-23T17:10:06+00:00","new":5,"old":6,"arena":4,"pirate":3},{"t":"2020-02-23T17:12:08+00:00","new":6,"old":5,"arena":4,"pirate":3},{"t":"2020-02-23T17:17:08+00:00","new":6,"old":7,"arena":2,"pirate":3},{"t":"2020-02-23T17:21:05+00:00","new":7,"old":6,"arena":2,"pirate":3},{"t":"2020-02-23T17:33:05+00:00","new":6,"old":7,"arena":2,"pirate":3},{"t":"2020-02-23T17:38:06+00:00","new":7,"old":6,"arena":2,"pirate":3},{"t":"2020-02-23T17:39:05+00:00","new":6,"old":7,"arena":2,"pirate":3},{"t":"2020-02-23T17:40:08+00:00","new":7,"old":6,"arena":2,"pirate":3},{"t":"2020-02-23T17:42:05+00:00","new":6,"old":7,"arena":2,"pirate":3},{"t":"2020-02-23T17:56:04+00:00","new":7,"old":6,"arena":2,"pirate":3},{"t":"2020-02-23T17:58:06+00:00","new":6,"old":7,"arena":2,"pirate":3},{"t":"2020-02-23T19:07:06+00:00","new":7,"old":6,"arena":2,"pirate":3},{"t":"2020-02-23T19:23:05+00:00","new":6,"old":7,"arena":2,"pirate":3},{"t":"2020-02-23T20:06:05+00:00","new":7,"old":6,"arena":2,"pirate":3},{"t":"2020-02-23T20:16:05+00:00","new":6,"old":4,"arena":1,"pirate":4},{"t":"2020-02-23T20:18:08+00:00","new":5,"old":6,"arena":1,"pirate":4},{"t":"2020-02-23T20:22:05+00:00","new":6,"old":5,"arena":1,"pirate":4},{"t":"2020-02-23T20:23:04+00:00","new":5,"old":6,"arena":1,"pirate":4},{"t":"2020-02-23T20:24:06+00:00","new":6,"old":5,"arena":1,"pirate":4},{"t":"2020-02-23T20:30:05+00:00","new":5,"old":6,"arena":1,"pirate":4},{"t":"2020-02-23T23:03:17+00:00","new":4,"old":5,"arena":1,"pirate":4}],"pirates":[[15,7,2,9],[1,14,16,18],[17,19,6,4],[8,5,13,11],[10,20,3,12]],"winners":[4,3,4,4,2],"timestamp":"2020-02-23T23:36:23+00:00","lastChange":"2020-02-23T23:03:17+00:00","lastUpdate":"2020-02-23T23:36:23+00:00","currentOdds":[[1,2,10,13,13],[1,2,13,2,4],[1,4,2,7,3],[1,11,2,3,4],[1,13,2,6,2]],"openingOdds":[[1,2,7,13,12],[1,2,13,2,4],[1,4,2,7,3],[1,11,2,3,4],[1,13,2,6,2]]}