{"foods":[[36,24,26,2,35,29,18,3,19,40],[27,1,28,18,2,33,37,9,8,40],[14,30,27,19,29,5,35,25,39,15],[12,6,40,27,15,36,3,31,19,34],[9,10,28,26,17,29,32,22,11,15]],"round":7629,"start":"2020-03-25T22:36:46+00:00","changes":[{"t":"2020-03-26T03:48:06+00:00","new":13,"old":11,"arena":2,"pirate":2},{"t":"2020-03-26T05:22:06+00:00","new":5,"old":6,"arena":1,"pirate":1},{"t":"2020-03-26T08:25:07+00:00","new":3,"old":4,"arena":3,"pirate":3},{"t":"2020-03-26T08:25:07+00:00","new":3,"old":2,"arena":3,"pirate":4},{"t":"2020-03-26T08:40:08+00:00","new":2,"old":3,"arena":3,"pirate":4},{"t":"2020-03-26T08:55:07+00:00","new":3,"old":2,"arena":3,"pirate":4},{"t":"2020-03-26T08:56:07+00:00","new":2,"old":3,"arena":3,"pirate":4},{"t":"2020-03-26T08:58:07+00:00","new":3,"old":2,"arena":3,"pirate":4},{"t":"2020-03-26T09:19:06+00:00","new":2,"old":3,"arena":3,"pirate":4},{"t":"2020-03-26T09:20:05+00:00","new":3,"old":2,"arena":3,"pirate":4},{"t":"2020-03-26T14:31:07+00:00","new":4,"old":3,"arena":3,"pirate":3},{"t":"2020-03-26T14:37:05+00:00","new":3,"old":4,"arena":3,"pirate":3},{"t":"2020-03-26T14:39:05+00:00","new":4,"old":3,"arena":3,"pirate":3},{"t":"2020-03-26T16:01:06+00:00","new":2,"old":3,"arena":3,"pirate":4},{"t":"2020-03-26T16:03:07+00:00","new":3,"old":2,"arena":3,"pirate":4},{"t":"2020-03-26T16:05:07+00:00","new":2,"old":3,"arena":3,"pirate":4},{"t":"2020-03-26T16:19:06+00:00","new":3,"old":2,"arena":3,"pirate":4},{"t":"2020-03-26T16:23:06+00:00","new":2,"old":3,"arena":3,"pirate":4},{"t":"2020-03-26T16:40:06+00:00","new":3,"old":2,"arena":3,"pirate":4},{"t":"2020-03-26T16:41:05+00:00","new":2,"old":3,"arena":3,"pirate":4}],"pirates":[[13,16,7,8],[19,20,3,17],[18,14,15,9],[11,12,2,6],[5,4,1,10]],"winners":[2,4,3,2,3],"timestamp":"2020-03-26T22:36:33+00:00","lastChange":"2020-03-26T16:41:05+00:00","lastUpdate":"2020-03-26T22:36:33+00:00","currentOdds":[[1,13,2,4,4],[1,5,2,13,2],[1,13,13,2,13],[1,10,3,4,2],[1,13,2,2,6]],"openingOdds":[[1,13,2,4,4],[1,6,2,13,2],[1,13,11,2,13],[1,10,3,4,2],[1,13,2,2,6]]}