{"foods":[[2,29,14,20,1,24,9,6,34,32],[11,25,34,36,31,21,16,6,13,35],[10,4,26,7,36,23,14,31,8,15],[30,27,37,25,17,5,21,22,20,19],[7,40,34,5,8,19,1,9,6,26]],"round":8627,"start":"2022-12-19T00:09:43+00:00","changes":[{"t":"2022-12-19T00:40:33+00:00","new":6,"old":5,"arena":4,"pirate":1},{"t":"2022-12-19T00:44:22+00:00","new":7,"old":5,"arena":3,"pirate":1},{"t":"2022-12-19T00:44:22+00:00","new":10,"old":8,"arena":3,"pirate":4},{"t":"2022-12-19T01:20:33+00:00","new":3,"old":2,"arena":2,"pirate":4},{"t":"2022-12-19T01:31:36+00:00","new":6,"old":7,"arena":2,"pirate":1},{"t":"2022-12-19T01:34:01+00:00","new":7,"old":6,"arena":2,"pirate":1},{"t":"2022-12-19T01:56:11+00:00","new":6,"old":7,"arena":2,"pirate":1},{"t":"2022-12-19T03:05:46+00:00","new":7,"old":6,"arena":2,"pirate":1},{"t":"2022-12-19T04:09:32+00:00","new":8,"old":7,"arena":1,"pirate":3},{"t":"2022-12-19T04:11:57+00:00","new":7,"old":8,"arena":1,"pirate":3},{"t":"2022-12-19T04:12:08+00:00","new":8,"old":7,"arena":1,"pirate":3},{"t":"2022-12-19T04:12:18+00:00","new":7,"old":8,"arena":1,"pirate":3},{"t":"2022-12-19T04:24:37+00:00","new":7,"old":6,"arena":4,"pirate":1},{"t":"2022-12-19T10:51:32+00:00","new":6,"old":7,"arena":2,"pirate":1},{"t":"2022-12-19T17:24:42+00:00","new":4,"old":3,"arena":0,"pirate":3},{"t":"2022-12-19T17:35:15+00:00","new":3,"old":4,"arena":0,"pirate":3},{"t":"2022-12-19T17:44:57+00:00","new":4,"old":3,"arena":0,"pirate":3},{"t":"2022-12-19T18:01:05+00:00","new":3,"old":4,"arena":0,"pirate":3},{"t":"2022-12-19T18:02:07+00:00","new":4,"old":3,"arena":0,"pirate":3},{"t":"2022-12-19T18:06:16+00:00","new":3,"old":4,"arena":0,"pirate":3},{"t":"2022-12-19T18:22:51+00:00","new":4,"old":3,"arena":0,"pirate":3},{"t":"2022-12-19T18:34:53+00:00","new":3,"old":4,"arena":0,"pirate":3},{"t":"2022-12-19T18:35:03+00:00","new":4,"old":3,"arena":0,"pirate":3},{"t":"2022-12-19T18:36:26+00:00","new":3,"old":4,"arena":0,"pirate":3},{"t":"2022-12-19T19:48:50+00:00","new":4,"old":3,"arena":0,"pirate":3},{"t":"2022-12-19T19:57:07+00:00","new":3,"old":4,"arena":0,"pirate":3},{"t":"2022-12-19T19:59:31+00:00","new":4,"old":3,"arena":0,"pirate":3},{"t":"2022-12-19T20:22:58+00:00","new":3,"old":4,"arena":0,"pirate":3},{"t":"2022-12-19T20:28:11+00:00","new":4,"old":3,"arena":0,"pirate":3},{"t":"2022-12-19T20:33:54+00:00","new":3,"old":4,"arena":0,"pirate":3},{"t":"2022-12-19T20:36:19+00:00","new":4,"old":3,"arena":0,"pirate":3},{"t":"2022-12-19T21:03:14+00:00","new":3,"old":4,"arena":0,"pirate":3}],"pirates":[[10,13,18,5],[19,11,6,4],[7,17,1,2],[3,14,20,9],[16,8,12,15]],"winners":[2,4,3,2,4],"timestamp":"2022-12-20T00:09:43+00:00","lastChange":"2022-12-19T21:03:14+00:00","currentOdds":[[1,13,3,3,2],[1,2,13,7,2],[1,6,13,2,3],[1,7,5,2,10],[1,7,13,13,2]],"openingOdds":[[1,13,3,3,2],[1,2,13,7,2],[1,7,13,2,2],[1,5,5,2,8],[1,5,13,13,2]]}