{"pirates":[[16,1,3,2],[8,20,12,6],[9,4,13,15],[14,19,17,18],[5,11,10,7]],"openingOdds":[[1,6,2,4,4],[1,7,2,4,5],[1,13,3,7,2],[1,13,2,2,4],[1,4,10,11,2]],"currentOdds":[[1,5,2,5,5],[1,8,2,4,5],[1,13,4,9,2],[1,13,2,2,4],[1,6,13,13,2]],"changes":[{"arena":4,"pirate":1,"old":4,"new":6,"t":"2024-04-01T00:04:14+00:00"},{"arena":4,"pirate":2,"old":10,"new":13,"t":"2024-04-01T00:04:14+00:00"},{"arena":4,"pirate":3,"old":11,"new":13,"t":"2024-04-01T00:04:14+00:00"},{"arena":2,"pirate":2,"old":3,"new":4,"t":"2024-04-01T00:04:32+00:00"},{"arena":2,"pirate":3,"old":7,"new":9,"t":"2024-04-01T00:04:32+00:00"},{"arena":1,"pirate":1,"old":7,"new":10,"t":"2024-04-01T00:11:05+00:00"},{"arena":1,"pirate":3,"old":4,"new":3,"t":"2024-04-01T00:11:05+00:00"},{"arena":1,"pirate":4,"old":5,"new":4,"t":"2024-04-01T00:11:05+00:00"},{"arena":0,"pirate":1,"old":6,"new":3,"t":"2024-04-01T00:29:11+00:00"},{"arena":0,"pirate":2,"old":2,"new":3,"t":"2024-04-01T00:29:11+00:00"},{"arena":0,"pirate":3,"old":4,"new":6,"t":"2024-04-01T00:29:11+00:00"},{"arena":0,"pirate":4,"old":4,"new":6,"t":"2024-04-01T00:29:11+00:00"},{"arena":1,"pirate":4,"old":4,"new":5,"t":"2024-04-01T01:53:12+00:00"},{"arena":1,"pirate":3,"old":3,"new":4,"t":"2024-04-01T01:53:47+00:00"},{"arena":1,"pirate":1,"old":10,"new":9,"t":"2024-04-01T03:03:38+00:00"},{"arena":0,"pirate":2,"old":3,"new":2,"t":"2024-04-01T03:07:28+00:00"},{"arena":0,"pirate":1,"old":3,"new":4,"t":"2024-04-01T07:33:48+00:00"},{"arena":0,"pirate":1,"old":4,"new":5,"t":"2024-04-01T11:49:50+00:00"},{"arena":1,"pirate":1,"old":9,"new":8,"t":"2024-04-01T15:07:45+00:00"},{"arena":0,"pirate":3,"old":6,"new":5,"t":"2024-04-01T15:57:43+00:00"},{"arena":0,"pirate":4,"old":6,"new":5,"t":"2024-04-01T16:09:01+00:00"},{"arena":3,"pirate":4,"old":4,"new":5,"t":"2024-04-01T19:44:33+00:00"},{"arena":3,"pirate":4,"old":5,"new":4,"t":"2024-04-01T20:17:32+00:00"}],"round":9096,"start":"2024-03-31T23:26:19+00:00","timestamp":"2024-04-01T23:25:23+00:00","lastChange":"2024-04-01T20:17:32+00:00","winners":[3,2,2,3,4],"foods":[[5,28,39,18,6,11,4,15,16,34],[40,23,36,26,25,24,15,18,11,3],[36,24,9,20,3,17,26,21,39,5],[35,15,34,4,7,17,37,16,19,9],[7,9,27,35,11,4,21,23,32,24]]}