{"pirates":[[14,3,15,19],[9,10,13,11],[20,8,12,5],[6,17,4,7],[16,18,2,1]],"openingOdds":[[1,13,12,3,2],[1,10,7,3,2],[1,2,13,3,3],[1,13,3,3,2],[1,5,12,13,2]],"currentOdds":[[1,13,13,3,2],[1,11,7,2,2],[1,2,13,2,2],[1,13,2,2,2],[1,7,13,13,2]],"changes":[{"arena":0,"pirate":2,"old":12,"new":13,"t":"2024-10-09T00:11:01+00:00"},{"arena":0,"pirate":3,"old":3,"new":2,"t":"2024-10-09T00:11:01+00:00"},{"arena":4,"pirate":1,"old":5,"new":4,"t":"2024-10-09T00:11:36+00:00"},{"arena":4,"pirate":2,"old":12,"new":13,"t":"2024-10-09T00:11:36+00:00"},{"arena":4,"pirate":1,"old":4,"new":5,"t":"2024-10-09T00:17:51+00:00"},{"arena":1,"pirate":1,"old":10,"new":12,"t":"2024-10-09T00:20:36+00:00"},{"arena":1,"pirate":1,"old":12,"new":11,"t":"2024-10-09T00:26:58+00:00"},{"arena":4,"pirate":1,"old":5,"new":6,"t":"2024-10-09T00:33:31+00:00"},{"arena":4,"pirate":1,"old":6,"new":7,"t":"2024-10-09T00:44:51+00:00"},{"arena":1,"pirate":3,"old":3,"new":2,"t":"2024-10-09T00:47:19+00:00"},{"arena":1,"pirate":3,"old":2,"new":3,"t":"2024-10-09T00:47:37+00:00"},{"arena":1,"pirate":3,"old":3,"new":2,"t":"2024-10-09T00:48:19+00:00"},{"arena":3,"pirate":3,"old":3,"new":2,"t":"2024-10-09T01:04:58+00:00"},{"arena":3,"pirate":2,"old":3,"new":2,"t":"2024-10-09T01:19:44+00:00"},{"arena":3,"pirate":2,"old":2,"new":3,"t":"2024-10-09T01:20:02+00:00"},{"arena":3,"pirate":2,"old":3,"new":2,"t":"2024-10-09T01:20:21+00:00"},{"arena":2,"pirate":4,"old":3,"new":2,"t":"2024-10-09T02:22:20+00:00"},{"arena":2,"pirate":4,"old":2,"new":3,"t":"2024-10-09T02:23:15+00:00"},{"arena":2,"pirate":3,"old":3,"new":2,"t":"2024-10-09T02:25:05+00:00"},{"arena":2,"pirate":4,"old":3,"new":2,"t":"2024-10-09T02:34:23+00:00"},{"arena":0,"pirate":3,"old":2,"new":3,"t":"2024-10-09T12:29:26+00:00"},{"arena":0,"pirate":3,"old":3,"new":2,"t":"2024-10-09T12:30:37+00:00"},{"arena":0,"pirate":3,"old":2,"new":3,"t":"2024-10-09T12:30:55+00:00"}],"round":9287,"start":"2024-10-08T23:31:53+00:00","timestamp":"2024-10-09T23:31:55+00:00","lastChange":"2024-10-09T12:30:55+00:00","winners":[3,3,1,2,4],"foods":[[21,4,20,37,31,7,2,40,25,14],[27,20,8,26,15,39,16,38,17,24],[1,14,6,12,25,24,3,34,21,9],[31,22,28,32,15,17,10,3,4,36],[39,14,25,21,17,8,35,19,27,23]]}